[
  {
    "id": "web-dev-bootcamp",
    "slug": "web-dev-bootcamp",
    "title": "Full-Stack Web Development Bootcamp",
    "description": "Master HTML, CSS, JavaScript, React, Node.js, and databases from scratch. Build real-world projects and land your first developer job.",
    "shortDescription": "Go from zero to full-stack developer with 80+ hours of content.",
    "category": "Technology",
    "level": "Beginner",
    "instructor": "Sarah Johnson",
    "instructorBio": "Senior Software Engineer at Google with 10+ years of experience teaching web development.",
    "instructorImage": "/instructors/sarah.jpg",
    "thumbnail": "/courses/web-dev.jpg",
    "duration": "80 hours",
    "lessons": 240,
    "students": 12500,
    "rating": 4.9,
    "reviews": 3200,
    "price": 89,
    "originalPrice": 199,
    "featured": true,
    "tags": ["HTML", "CSS", "JavaScript", "React", "Node.js", "MongoDB"],
    "curriculum": [
      { "title": "HTML & CSS Fundamentals", "lessons": 30, "duration": "10h" },
      { "title": "JavaScript Essentials", "lessons": 45, "duration": "15h" },
      { "title": "React & Modern Frontend", "lessons": 60, "duration": "20h" },
      { "title": "Node.js & Express Backend", "lessons": 50, "duration": "17h" },
      { "title": "Databases & Deployment", "lessons": 55, "duration": "18h" }
    ],
    "requirements": ["A computer with internet access", "No prior coding experience needed", "Willingness to learn"],
    "whatYouLearn": ["Build modern websites from scratch", "Create full-stack web applications", "Work with databases and APIs", "Deploy apps to the cloud"],
    "published": true,
    "createdAt": "2024-01-15",
    "updatedAt": "2024-03-20"
  },
  {
    "id": "data-science-ml",
    "slug": "data-science-ml",
    "title": "Data Science & Machine Learning with Python",
    "description": "Learn data analysis, visualization, and machine learning with Python, Pandas, NumPy, Scikit-learn, and TensorFlow through hands-on projects.",
    "shortDescription": "Master data science and ML with real-world Python projects.",
    "category": "Technology",
    "level": "Intermediate",
    "instructor": "Dr. Michael Chen",
    "instructorBio": "PhD in Computer Science, former Data Scientist at Netflix and Tesla.",
    "instructorImage": "/instructors/michael.jpg",
    "thumbnail": "/courses/data-science.jpg",
    "duration": "65 hours",
    "lessons": 195,
    "students": 8900,
    "rating": 4.8,
    "reviews": 2100,
    "price": 99,
    "originalPrice": 249,
    "featured": true,
    "tags": ["Python", "Machine Learning", "Data Science", "TensorFlow", "Pandas"],
    "curriculum": [
      { "title": "Python for Data Science", "lessons": 35, "duration": "12h" },
      { "title": "Data Analysis with Pandas", "lessons": 40, "duration": "13h" },
      { "title": "Data Visualization", "lessons": 30, "duration": "10h" },
      { "title": "Machine Learning Fundamentals", "lessons": 50, "duration": "17h" },
      { "title": "Deep Learning with TensorFlow", "lessons": 40, "duration": "13h" }
    ],
    "requirements": ["Basic Python knowledge", "High school math", "A computer with 8GB+ RAM"],
    "whatYouLearn": ["Analyze complex datasets", "Build ML models from scratch", "Create data visualizations", "Deploy ML models to production"],
    "published": true,
    "createdAt": "2024-02-01",
    "updatedAt": "2024-03-25"
  },
  {
    "id": "ux-ui-design",
    "slug": "ux-ui-design",
    "title": "UX/UI Design Masterclass",
    "description": "Design beautiful, user-centered digital products. Learn Figma, design principles, user research, prototyping, and build a stunning portfolio.",
    "shortDescription": "Become a professional UX/UI designer with Figma and design thinking.",
    "category": "Design",
    "level": "Beginner",
    "instructor": "Emma Rodriguez",
    "instructorBio": "Lead UX Designer at Apple, speaker at design conferences worldwide.",
    "instructorImage": "/instructors/emma.jpg",
    "thumbnail": "/courses/ux-design.jpg",
    "duration": "50 hours",
    "lessons": 150,
    "students": 6700,
    "rating": 4.9,
    "reviews": 1800,
    "price": 79,
    "originalPrice": 179,
    "featured": true,
    "tags": ["Figma", "UX Design", "UI Design", "Prototyping", "User Research"],
    "curriculum": [
      { "title": "Design Thinking & UX Fundamentals", "lessons": 25, "duration": "8h" },
      { "title": "Figma Mastery", "lessons": 35, "duration": "12h" },
      { "title": "User Research & Testing", "lessons": 30, "duration": "10h" },
      { "title": "Visual Design & Typography", "lessons": 30, "duration": "10h" },
      { "title": "Portfolio & Career", "lessons": 30, "duration": "10h" }
    ],
    "requirements": ["No design experience required", "A computer (Mac or Windows)", "Figma free account"],
    "whatYouLearn": ["Master Figma from beginner to advanced", "Conduct user research", "Create interactive prototypes", "Build a professional portfolio"],
    "published": true,
    "createdAt": "2024-01-28",
    "updatedAt": "2024-03-18"
  },
  {
    "id": "digital-marketing",
    "slug": "digital-marketing",
    "title": "Digital Marketing Complete Guide",
    "description": "Learn SEO, social media marketing, email marketing, Google Ads, content marketing, and analytics to grow any business online.",
    "shortDescription": "Master every digital marketing channel to grow business online.",
    "category": "Business",
    "level": "Beginner",
    "instructor": "James Wilson",
    "instructorBio": "Growth Marketing Lead with experience scaling 50+ startups.",
    "instructorImage": "/instructors/james.jpg",
    "thumbnail": "/courses/digital-marketing.jpg",
    "duration": "45 hours",
    "lessons": 135,
    "students": 9200,
    "rating": 4.7,
    "reviews": 2400,
    "price": 69,
    "originalPrice": 149,
    "featured": false,
    "tags": ["SEO", "Google Ads", "Social Media", "Email Marketing", "Analytics"],
    "curriculum": [
      { "title": "Digital Marketing Foundations", "lessons": 20, "duration": "7h" },
      { "title": "SEO & Content Marketing", "lessons": 30, "duration": "10h" },
      { "title": "Social Media Marketing", "lessons": 25, "duration": "8h" },
      { "title": "Paid Advertising (Google & Meta)", "lessons": 35, "duration": "12h" },
      { "title": "Analytics & Optimization", "lessons": 25, "duration": "8h" }
    ],
    "requirements": ["No prior marketing experience needed", "A computer and internet connection"],
    "whatYouLearn": ["Rank websites on Google", "Run profitable ad campaigns", "Build engaged social media audiences", "Measure and optimize campaigns"],
    "published": true,
    "createdAt": "2024-02-10",
    "updatedAt": "2024-03-22"
  }
]
